{"metadata": {"dbt_schema_version": "https://schemas.getdbt.com/dbt/run-results/v6.json", "dbt_version": "1.10.13", "generated_at": "2025-10-15T21:42:18.350131Z", "invocation_id": "d06620a0-af34-4f25-b40e-cc44b2ba4c0e", "invocation_started_at": "2025-10-15T21:42:17.067093Z", "env": {}}, "results": [{"status": "success", "timing": [{"name": "compile", "started_at": "2025-10-15T21:42:18.197440Z", "completed_at": "2025-10-15T21:42:18.299328Z"}, {"name": "execute", "started_at": "2025-10-15T21:42:18.299731Z", "completed_at": "2025-10-15T21:42:18.299736Z"}], "thread_id": "main", "execution_time": 0.102296, "adapter_response": {}, "message": "cg_lakehouse.on-run-start.0 passed", "failures": 0, "unique_id": "operation.cg_lakehouse.cg_lakehouse-on-run-start-0", "compiled": true, "compiled_code": "\n  \n  \n  \n  \n  \n  \n\n  \n  \n  \n  \n  \n  \n  \n\n  \n  \n  \n  \n\n  \n  \n  \n\n  \n  \n  \n  \n  \n\n  \n  \n\n  \n    \n  \n    \n  \n    \n  \n    \n  \n    \n  \n    \n  \n    \n  \n    \n  \n    \n  \n    \n  \n    \n  \n    \n  \n    \n  \n    \n  \n    \n  \n\n  \n  \n\n  \n  \n\n  \n  \n\n  \n  \n  \n    \n      \n    \n  \n\n  \n    \n    \n  \n\n  \n\n  \n\n  \n    \n  \n    \n  \n    \n  \n    \n  \n    \n  \n    \n  \n    \n  \n\n  \n", "relation_name": null, "batch_results": null}, {"status": "error", "timing": [{"name": "compile", "started_at": "2025-10-15T21:42:18.303789Z", "completed_at": "2025-10-15T21:42:18.307108Z"}, {"name": "execute", "started_at": "2025-10-15T21:42:18.307458Z", "completed_at": "2025-10-15T21:42:18.335129Z"}], "thread_id": "Thread-1 (worker)", "execution_time": 0.036203622817993164, "adapter_response": {}, "message": "Runtime Error in model stg_entries (models/bronze/stg_entries.sql)\n  Catalog Error: Table with name entries does not exist!\n  Did you mean \"__ducklake_metadata_ducklake.information_schema.triggers\"?\n  \n  LINE 16:     select * from \"ducklake\".\"bronze\".\"entries\"\n                             ^", "failures": null, "unique_id": "model.cg_lakehouse.stg_entries", "compiled": true, "compiled_code": "\n\n-- Staging model for Nightscout glucose readings\n-- This model reads raw data from DuckLake bronze layer and provides a clean,\n-- typed view of glucose data. It serves as the foundation for downstream\n-- transformations.\n-- Source: DLT ingestion into DuckLake bronze.entries\n-- Refresh: On-demand via Dagster\n-- Partitioning: Supports daily partition filtering via partition_date_str variable\n\nwith raw_data as (\n    select * from \"ducklake\".\"bronze\".\"entries\"\n)\n\nselect\n    _id as entry_id,\n    sgv as glucose_mg_dl,\n    epoch_ms(date) as reading_timestamp,\n    dateString as timestamp_iso,\n    direction,\n    trend,\n    device,\n    type as reading_type,\n    utcOffset as utc_offset_minutes\nfrom raw_data\nwhere sgv is not null\n    and sgv between 20 and 600  -- Physiologically plausible range\n    \n    -- Filter to partition date when processing partitioned data\n    and date_trunc('day', epoch_ms(date)) = '2025-10-14'::DATE\n    ", "relation_name": "\"memory\".\"main_bronze\".\"stg_entries\"", "batch_results": null}, {"status": "skipped", "timing": [], "thread_id": "Thread-3 (worker)", "execution_time": 0, "adapter_response": {}, "message": null, "failures": null, "unique_id": "model.cg_lakehouse.fct_glucose_readings", "compiled": false, "compiled_code": null, "relation_name": "\"memory\".\"main_silver\".\"fct_glucose_readings\"", "batch_results": null}], "elapsed_time": 0.3458578586578369, "args": {"show_resource_report": false, "empty": false, "require_generic_test_arguments_property": true, "require_yaml_configuration_for_mf_time_spines": false, "use_colors_file": true, "printer_width": 80, "log_file_max_bytes": 10485760, "state_modified_compare_more_unrendered_values": false, "skip_nodes_if_on_run_start_fails": false, "validate_macro_args": false, "which": "build", "log_format": "json", "require_explicit_package_overrides_for_builtin_materializations": true, "write_json": true, "state_modified_compare_vars": false, "log_format_file": "json", "target_path": "target/all_dbt_assets-533db45-e36f194", "invocation_command": "dbt build --project-dir /dbt --profiles-dir /dbt/profiles --target ducklake --vars {\"partition_date_str\": \"2025-10-14\"} --select cg_lakehouse.silver.fct_glucose_readings cg_lakehouse.bronze.stg_entries", "log_level": "info", "log_level_file": "debug", "partial_parse": true, "print": true, "upload_to_artifacts_ingest_api": false, "include_saved_query": false, "use_fast_test_edges": false, "warn_error_options": {"error": [], "warn": [], "silence": []}, "require_nested_cumulative_type_params": false, "introspect": true, "version_check": true, "exclude": [], "strict_mode": false, "vars": {"partition_date_str": "2025-10-14"}, "defer": false, "partial_parse_file_diff": true, "source_freshness_run_project_hooks": true, "profiles_dir": "/dbt/profiles", "resource_types": [], "select": ["cg_lakehouse.silver.fct_glucose_readings", "cg_lakehouse.bronze.stg_entries"], "static_parser": true, "use_colors": true, "target": "ducklake", "show": false, "favor_state": false, "populate_cache": true, "require_all_warnings_handled_by_warn_error": false, "require_resource_names_without_spaces": true, "indirect_selection": "eager", "log_path": "/dbt/target/all_dbt_assets-533db45-e36f194", "quiet": false, "project_dir": "/dbt", "send_anonymous_usage_stats": false, "exclude_resource_types": [], "cache_selected_only": false, "macro_debugging": false, "show_all_deprecations": false, "export_saved_queries": false, "require_batched_execution_for_custom_microbatch_strategy": false}}